taiwanbus/__init__.py
taiwanbus/__main__.py
taiwanbus/api.py
taiwanbus/cache.py
taiwanbus/exceptions.py
taiwanbus/session.py
taiwanbus-0.1.1.dist-info/licenses/LICENSE
taiwanbus-0.1.1.dist-info/METADATA
taiwanbus-0.1.1.dist-info/WHEEL
taiwanbus-0.1.1.dist-info/entry_points.txt
taiwanbus-0.1.1.dist-info/top_level.txt
taiwanbus-0.1.1.dist-info/RECORD
